setup.py
qiniu4blog/__init__.py
qiniu4blog/qiniu4blog.py
qiniu4blog.egg-info/PKG-INFO
qiniu4blog.egg-info/SOURCES.txt
qiniu4blog.egg-info/dependency_links.txt
qiniu4blog.egg-info/entry_points.txt
qiniu4blog.egg-info/not-zip-safe
qiniu4blog.egg-info/requires.txt
qiniu4blog.egg-info/top_level.txt