Metadata-Version: 1.0
Name: qiniu4blog
Version: 1.4.0
Summary: 写博客用的七牛图床
Home-page: https://github.com/wzyuliyang/qiniu4blog
Author: wzyuliyang
Author-email: wzyuliyang911@gmail.com
License: MIT License
Keywords: python qiniu
Platform: UNKNOWN
